AFK/__init__.py
AFK/afk.py
AFKer-0.1.0.dist-info/LICENSE
AFKer-0.1.0.dist-info/METADATA
AFKer-0.1.0.dist-info/WHEEL
AFKer-0.1.0.dist-info/top_level.txt
AFKer-0.1.0.dist-info/RECORD
