Metadata-Version: 2.1
Name: AFKer
Version: 0.1.0
Summary: AFK script
Home-page: https://github.com/LiamMcFadden/AFKer
Author: Liam McFadden
Author-email: liamm18@vt.edu
License: UNKNOWN
Keywords: afk video games
Platform: UNKNOWN
Requires-Python: >=3.6
Requires-Dist: keyboard
Requires-Dist: pyautogui
